.gitignore
CHANGES.txt
CONTRIBUTORS.txt
MANIFEST.in
README.rst
setup.py
docs/LICENSE.GPL
docs/LICENSE.txt
docs/MANUAL.txt
src/raptus/__init__.py
src/raptus.article.mediagallery.egg-info/PKG-INFO
src/raptus.article.mediagallery.egg-info/SOURCES.txt
src/raptus.article.mediagallery.egg-info/dependency_links.txt
src/raptus.article.mediagallery.egg-info/entry_points.txt
src/raptus.article.mediagallery.egg-info/namespace_packages.txt
src/raptus.article.mediagallery.egg-info/not-zip-safe
src/raptus.article.mediagallery.egg-info/requires.txt
src/raptus.article.mediagallery.egg-info/top_level.txt
src/raptus/article/__init__.py
src/raptus/article/mediagallery/__init__.py
src/raptus/article/mediagallery/configure.zcml
src/raptus/article/mediagallery/extender.py
src/raptus/article/mediagallery/setuphandlers.py
src/raptus/article/mediagallery/browser/__init__.py
src/raptus/article/mediagallery/browser/configure.zcml
src/raptus/article/mediagallery/browser/mediagallery.gif
src/raptus/article/mediagallery/browser/mediagallery.js
src/raptus/article/mediagallery/browser/mediagallery.pt
src/raptus/article/mediagallery/browser/mediagallery.py
src/raptus/article/mediagallery/i18n/raptus.article-de.mo
src/raptus/article/mediagallery/i18n/raptus.article-de.po
src/raptus/article/mediagallery/i18n/raptus.article-fr.mo
src/raptus/article/mediagallery/i18n/raptus.article-fr.po
src/raptus/article/mediagallery/i18n/raptus.article.pot
src/raptus/article/mediagallery/profiles/default/cssregistry.xml
src/raptus/article/mediagallery/profiles/default/jsregistry.xml
src/raptus/article/mediagallery/profiles/default/metadata.xml
src/raptus/article/mediagallery/profiles/default/propertiestool.xml
src/raptus/article/mediagallery/profiles/default/raptus.article.mediagallery_install.txt
src/raptus/article/mediagallery/profiles/default/skins.xml
src/raptus/article/mediagallery/profiles/default/viewlets.xml
src/raptus/article/mediagallery/skins/raptus_article_mediagallery/raptus.article.mediagallery.css.dtml