Metadata-Version: 1.0
Name: raptus.article.mediagallery
Version: 1.0a4
Summary: Provides a horizontal and optionally grouped media gallery able to render images and movies
Home-page: http://github.com/Raptus/raptus.article.mediagallery
Author: Raptus AG
Author-email: dev@raptus.com
License: gpl
Platform: UNKNOWN
Classifier: Programming Language :: Python
